LICENSE
README.md
setup.py
mySecrets/__init__.py
mySecrets/crypt.py
mySecrets/exceptions.py
mySecrets/hash.py
mySecrets/jtc64.py
mySecrets.egg-info/PKG-INFO
mySecrets.egg-info/SOURCES.txt
mySecrets.egg-info/dependency_links.txt
mySecrets.egg-info/entry_points.txt
mySecrets.egg-info/top_level.txt