Metadata-Version: 2.1
Name: mySecrets
Version: 0.9.0
Summary: Very secure hash and symmetrical encryption
Home-page: https://github.com/jtc1246/mySecrets
Author: Tiancheng Jiao
Author-email: jtc1246@outlook.com
License: GPL-2.0 License
Platform: all
Requires-Python: >=3
License-File: LICENSE
